<?xml version="1.0" encoding="utf-8"?>
<BindInfo>
	<BindNode BINDTYPE="op" DISPLAY="bind_op mul" ID="" IMPL="auto" LATENCY="0" OPTYPE="mul" PRAGMA="" RTLNAME="mul_32s_32s_32_1_1_U5" SOURCE="/home/ytq/codeField/Prediction_Model_Accelerator/CSIM/Sparse_HLS/Sparse_HLS/src/../include/helpers.hpp:20" VARIABLE="mul_ln20" MODULE="load_ap_uint_256_ap_int_8_32u_s" LOOP="" BUNDLEDNAME="" DSP="3" BRAM="0" URAM="0"/>
	<BindNode BINDTYPE="op" DISPLAY="bind_op icmp" ID="" IMPL="auto" LATENCY="0" OPTYPE="icmp" PRAGMA="" RTLNAME="exitcond7_fu_276_p2" SOURCE="/home/ytq/codeField/Prediction_Model_Accelerator/CSIM/Sparse_HLS/Sparse_HLS/src/../include/helpers.hpp:20" VARIABLE="exitcond7" MODULE="load_ap_uint_256_ap_int_8_32u_s" LOOP="Loop 1" BUNDLEDNAME="" DSP="0" BRAM="0" URAM="0"/>
	<BindNode BINDTYPE="op" DISPLAY="bind_op add" ID="" IMPL="fabric" LATENCY="0" OPTYPE="add" PRAGMA="" RTLNAME="empty_fu_281_p2" SOURCE="" VARIABLE="empty" MODULE="load_ap_uint_256_ap_int_8_32u_s" LOOP="Loop 1" BUNDLEDNAME="" DSP="0" BRAM="0" URAM="0"/>
	<BindNode BINDTYPE="op" DISPLAY="bind_op add" ID="" IMPL="fabric" LATENCY="0" OPTYPE="add" PRAGMA="" RTLNAME="tmp_fu_291_p2" SOURCE="/home/ytq/codeField/Prediction_Model_Accelerator/CSIM/Sparse_HLS/Sparse_HLS/src/../include/helpers.hpp:20" VARIABLE="tmp" MODULE="load_ap_uint_256_ap_int_8_32u_s" LOOP="Loop 1" BUNDLEDNAME="" DSP="0" BRAM="0" URAM="0"/>
	<BindNode BINDTYPE="op" DISPLAY="bind_op add" ID="" IMPL="fabric" LATENCY="0" OPTYPE="add" PRAGMA="" RTLNAME="empty_43_fu_300_p2" SOURCE="/home/ytq/codeField/Prediction_Model_Accelerator/CSIM/Sparse_HLS/Sparse_HLS/src/../include/helpers.hpp:20" VARIABLE="empty_43" MODULE="load_ap_uint_256_ap_int_8_32u_s" LOOP="Loop 1" BUNDLEDNAME="" DSP="0" BRAM="0" URAM="0"/>
	<BindNode BINDTYPE="op" DISPLAY="bind_op add" ID="" IMPL="fabric" LATENCY="0" OPTYPE="add" PRAGMA="" RTLNAME="empty_44_fu_350_p2" SOURCE="/home/ytq/codeField/Prediction_Model_Accelerator/CSIM/Sparse_HLS/Sparse_HLS/src/../include/helpers.hpp:20" VARIABLE="empty_44" MODULE="load_ap_uint_256_ap_int_8_32u_s" LOOP="Loop 1" BUNDLEDNAME="" DSP="0" BRAM="0" URAM="0"/>
	<BindNode BINDTYPE="op" DISPLAY="bind_op lshr" ID="" IMPL="auto_pipe" LATENCY="0" OPTYPE="lshr" PRAGMA="" RTLNAME="empty_45_fu_365_p2" SOURCE="/home/ytq/codeField/Prediction_Model_Accelerator/CSIM/Sparse_HLS/Sparse_HLS/src/../include/helpers.hpp:20" VARIABLE="empty_45" MODULE="load_ap_uint_256_ap_int_8_32u_s" LOOP="Loop 1" BUNDLEDNAME="" DSP="0" BRAM="0" URAM="0"/>
	<BindNode BINDTYPE="op" DISPLAY="bind_op mul" ID="" IMPL="auto" LATENCY="0" OPTYPE="mul" PRAGMA="" RTLNAME="mul_32s_32s_32_1_1_U6" SOURCE="/home/ytq/codeField/Prediction_Model_Accelerator/CSIM/Sparse_HLS/Sparse_HLS/src/../include/helpers.hpp:21" VARIABLE="mul_ln21" MODULE="load_ap_uint_256_ap_int_8_32u_s" LOOP="" BUNDLEDNAME="" DSP="3" BRAM="0" URAM="0"/>
	<BindNode BINDTYPE="op" DISPLAY="bind_op icmp" ID="" IMPL="auto" LATENCY="0" OPTYPE="icmp" PRAGMA="" RTLNAME="exitcond6_fu_382_p2" SOURCE="/home/ytq/codeField/Prediction_Model_Accelerator/CSIM/Sparse_HLS/Sparse_HLS/src/../include/helpers.hpp:21" VARIABLE="exitcond6" MODULE="load_ap_uint_256_ap_int_8_32u_s" LOOP="Loop 2" BUNDLEDNAME="" DSP="0" BRAM="0" URAM="0"/>
	<BindNode BINDTYPE="op" DISPLAY="bind_op add" ID="" IMPL="fabric" LATENCY="0" OPTYPE="add" PRAGMA="" RTLNAME="empty_47_fu_387_p2" SOURCE="" VARIABLE="empty_47" MODULE="load_ap_uint_256_ap_int_8_32u_s" LOOP="Loop 2" BUNDLEDNAME="" DSP="0" BRAM="0" URAM="0"/>
	<BindNode BINDTYPE="op" DISPLAY="bind_op add" ID="" IMPL="fabric" LATENCY="0" OPTYPE="add" PRAGMA="" RTLNAME="tmp2_fu_397_p2" SOURCE="/home/ytq/codeField/Prediction_Model_Accelerator/CSIM/Sparse_HLS/Sparse_HLS/src/../include/helpers.hpp:21" VARIABLE="tmp2" MODULE="load_ap_uint_256_ap_int_8_32u_s" LOOP="Loop 2" BUNDLEDNAME="" DSP="0" BRAM="0" URAM="0"/>
	<BindNode BINDTYPE="op" DISPLAY="bind_op add" ID="" IMPL="fabric" LATENCY="0" OPTYPE="add" PRAGMA="" RTLNAME="empty_49_fu_406_p2" SOURCE="/home/ytq/codeField/Prediction_Model_Accelerator/CSIM/Sparse_HLS/Sparse_HLS/src/../include/helpers.hpp:21" VARIABLE="empty_49" MODULE="load_ap_uint_256_ap_int_8_32u_s" LOOP="Loop 2" BUNDLEDNAME="" DSP="0" BRAM="0" URAM="0"/>
	<BindNode BINDTYPE="op" DISPLAY="bind_op add" ID="" IMPL="fabric" LATENCY="0" OPTYPE="add" PRAGMA="" RTLNAME="empty_50_fu_421_p2" SOURCE="/home/ytq/codeField/Prediction_Model_Accelerator/CSIM/Sparse_HLS/Sparse_HLS/src/../include/helpers.hpp:20" VARIABLE="empty_50" MODULE="load_ap_uint_256_ap_int_8_32u_s" LOOP="Loop 2" BUNDLEDNAME="" DSP="0" BRAM="0" URAM="0"/>
	<BindNode BINDTYPE="op" DISPLAY="bind_op lshr" ID="" IMPL="auto_pipe" LATENCY="0" OPTYPE="lshr" PRAGMA="" RTLNAME="empty_51_fu_471_p2" SOURCE="/home/ytq/codeField/Prediction_Model_Accelerator/CSIM/Sparse_HLS/Sparse_HLS/src/../include/helpers.hpp:21" VARIABLE="empty_51" MODULE="load_ap_uint_256_ap_int_8_32u_s" LOOP="Loop 2" BUNDLEDNAME="" DSP="0" BRAM="0" URAM="0"/>
	<BindNode BINDTYPE="op" DISPLAY="bind_op icmp" ID="" IMPL="auto" LATENCY="0" OPTYPE="icmp" PRAGMA="" RTLNAME="icmp_ln1023_fu_434_p2" SOURCE="/home/ytq/source/Xilinx/Vitis_HLS/2022.2/common/technology/autopilot/ap_int_base.h:1023" VARIABLE="icmp_ln1023" MODULE="load_ap_uint_256_ap_int_8_32u_s" LOOP="" BUNDLEDNAME="" DSP="0" BRAM="0" URAM="0"/>
	<BindNode BINDTYPE="op" DISPLAY="bind_op icmp" ID="" IMPL="auto" LATENCY="0" OPTYPE="icmp" PRAGMA="" RTLNAME="icmp_ln23_fu_492_p2" SOURCE="/home/ytq/codeField/Prediction_Model_Accelerator/CSIM/Sparse_HLS/Sparse_HLS/src/../include/helpers.hpp:23" VARIABLE="icmp_ln23" MODULE="load_ap_uint_256_ap_int_8_32u_s" LOOP="VITIS_LOOP_23_1" BUNDLEDNAME="" DSP="0" BRAM="0" URAM="0"/>
	<BindNode BINDTYPE="op" DISPLAY="bind_op add" ID="" IMPL="fabric" LATENCY="0" OPTYPE="add" PRAGMA="" RTLNAME="add_ln32_fu_497_p2" SOURCE="/home/ytq/codeField/Prediction_Model_Accelerator/CSIM/Sparse_HLS/Sparse_HLS/src/../include/helpers.hpp:32" VARIABLE="add_ln32" MODULE="load_ap_uint_256_ap_int_8_32u_s" LOOP="VITIS_LOOP_23_1" BUNDLEDNAME="" DSP="0" BRAM="0" URAM="0"/>
	<BindNode BINDTYPE="op" DISPLAY="bind_op icmp" ID="" IMPL="auto" LATENCY="0" OPTYPE="icmp" PRAGMA="" RTLNAME="icmp_ln26_fu_513_p2" SOURCE="/home/ytq/codeField/Prediction_Model_Accelerator/CSIM/Sparse_HLS/Sparse_HLS/src/../include/helpers.hpp:26" VARIABLE="icmp_ln26" MODULE="load_ap_uint_256_ap_int_8_32u_s" LOOP="VITIS_LOOP_26_2" BUNDLEDNAME="" DSP="0" BRAM="0" URAM="0"/>
	<BindNode BINDTYPE="op" DISPLAY="bind_op add" ID="" IMPL="fabric" LATENCY="0" OPTYPE="add" PRAGMA="" RTLNAME="add_ln26_fu_518_p2" SOURCE="/home/ytq/codeField/Prediction_Model_Accelerator/CSIM/Sparse_HLS/Sparse_HLS/src/../include/helpers.hpp:26" VARIABLE="add_ln26" MODULE="load_ap_uint_256_ap_int_8_32u_s" LOOP="VITIS_LOOP_26_2" BUNDLEDNAME="" DSP="0" BRAM="0" URAM="0"/>
	<BindNode BINDTYPE="op" DISPLAY="bind_op add" ID="" IMPL="fabric" LATENCY="0" OPTYPE="add" PRAGMA="" RTLNAME="count_2_fu_527_p2" SOURCE="/home/ytq/codeField/Prediction_Model_Accelerator/CSIM/Sparse_HLS/Sparse_HLS/src/../include/helpers.hpp:28" VARIABLE="count_2" MODULE="load_ap_uint_256_ap_int_8_32u_s" LOOP="VITIS_LOOP_26_2" BUNDLEDNAME="" DSP="0" BRAM="0" URAM="0"/>
	<BindNode BINDTYPE="op" DISPLAY="bind_op add" ID="" IMPL="fabric" LATENCY="0" OPTYPE="add" PRAGMA="" RTLNAME="idx_count_1_fu_538_p2" SOURCE="/home/ytq/codeField/Prediction_Model_Accelerator/CSIM/Sparse_HLS/Sparse_HLS/src/../include/helpers.hpp:29" VARIABLE="idx_count_1" MODULE="load_ap_uint_256_ap_int_8_32u_s" LOOP="VITIS_LOOP_26_2" BUNDLEDNAME="" DSP="0" BRAM="0" URAM="0"/>
	<BindNode BINDTYPE="op" DISPLAY="bind_op icmp" ID="" IMPL="auto" LATENCY="0" OPTYPE="icmp" PRAGMA="" RTLNAME="icmp_ln49_fu_910_p2" SOURCE="/home/ytq/codeField/Prediction_Model_Accelerator/CSIM/Sparse_HLS/Sparse_HLS/src/../include/helpers.hpp:49" VARIABLE="icmp_ln49" MODULE="mul_ap_uint_256_ap_int_8_ap_int_8_32u_s" LOOP="VITIS_LOOP_49_1" BUNDLEDNAME="" DSP="0" BRAM="0" URAM="0"/>
	<BindNode BINDTYPE="op" DISPLAY="bind_op add" ID="" IMPL="fabric" LATENCY="0" OPTYPE="add" PRAGMA="" RTLNAME="block_2_fu_915_p2" SOURCE="/home/ytq/codeField/Prediction_Model_Accelerator/CSIM/Sparse_HLS/Sparse_HLS/src/../include/helpers.hpp:49" VARIABLE="block_2" MODULE="mul_ap_uint_256_ap_int_8_ap_int_8_32u_s" LOOP="VITIS_LOOP_49_1" BUNDLEDNAME="" DSP="0" BRAM="0" URAM="0"/>
	<BindNode BINDTYPE="op" DISPLAY="bind_op icmp" ID="" IMPL="auto" LATENCY="0" OPTYPE="icmp" PRAGMA="" RTLNAME="icmp_ln51_fu_938_p2" SOURCE="/home/ytq/codeField/Prediction_Model_Accelerator/CSIM/Sparse_HLS/Sparse_HLS/src/../include/helpers.hpp:51" VARIABLE="icmp_ln51" MODULE="mul_ap_uint_256_ap_int_8_ap_int_8_32u_s" LOOP="VITIS_LOOP_51_2" BUNDLEDNAME="" DSP="0" BRAM="0" URAM="0"/>
	<BindNode BINDTYPE="op" DISPLAY="bind_op add" ID="" IMPL="fabric" LATENCY="0" OPTYPE="add" PRAGMA="" RTLNAME="add_ln51_fu_943_p2" SOURCE="/home/ytq/codeField/Prediction_Model_Accelerator/CSIM/Sparse_HLS/Sparse_HLS/src/../include/helpers.hpp:51" VARIABLE="add_ln51" MODULE="mul_ap_uint_256_ap_int_8_ap_int_8_32u_s" LOOP="VITIS_LOOP_51_2" BUNDLEDNAME="" DSP="0" BRAM="0" URAM="0"/>
	<BindNode BINDTYPE="op" DISPLAY="bind_op icmp" ID="" IMPL="auto" LATENCY="0" OPTYPE="icmp" PRAGMA="" RTLNAME="icmp_ln56_fu_965_p2" SOURCE="/home/ytq/codeField/Prediction_Model_Accelerator/CSIM/Sparse_HLS/Sparse_HLS/src/../include/helpers.hpp:56" VARIABLE="icmp_ln56" MODULE="mul_ap_uint_256_ap_int_8_ap_int_8_32u_s" LOOP="VITIS_LOOP_56_3" BUNDLEDNAME="" DSP="0" BRAM="0" URAM="0"/>
	<BindNode BINDTYPE="op" DISPLAY="bind_op add" ID="" IMPL="fabric" LATENCY="0" OPTYPE="add" PRAGMA="" RTLNAME="add_ln56_fu_970_p2" SOURCE="/home/ytq/codeField/Prediction_Model_Accelerator/CSIM/Sparse_HLS/Sparse_HLS/src/../include/helpers.hpp:56" VARIABLE="add_ln56" MODULE="mul_ap_uint_256_ap_int_8_ap_int_8_32u_s" LOOP="VITIS_LOOP_56_3" BUNDLEDNAME="" DSP="0" BRAM="0" URAM="0"/>
	<BindNode BINDTYPE="op" DISPLAY="bind_op add" ID="" IMPL="fabric" LATENCY="0" OPTYPE="add" PRAGMA="" RTLNAME="add_ln57_fu_976_p2" SOURCE="/home/ytq/codeField/Prediction_Model_Accelerator/CSIM/Sparse_HLS/Sparse_HLS/src/../include/helpers.hpp:57" VARIABLE="add_ln57" MODULE="mul_ap_uint_256_ap_int_8_ap_int_8_32u_s" LOOP="VITIS_LOOP_56_3" BUNDLEDNAME="" DSP="0" BRAM="0" URAM="0"/>
	<BindNode BINDTYPE="op" DISPLAY="bind_op add" ID="" IMPL="fabric" LATENCY="0" OPTYPE="add" PRAGMA="" RTLNAME="add17_fu_1064_p2" SOURCE="/home/ytq/codeField/Prediction_Model_Accelerator/CSIM/Sparse_HLS/Sparse_HLS/src/../include/helpers.hpp:57" VARIABLE="add17" MODULE="mul_ap_uint_256_ap_int_8_ap_int_8_32u_s" LOOP="VITIS_LOOP_56_3" BUNDLEDNAME="" DSP="0" BRAM="0" URAM="0"/>
	<BindNode BINDTYPE="op" DISPLAY="bind_op add" ID="" IMPL="fabric" LATENCY="0" OPTYPE="add" PRAGMA="" RTLNAME="add_ln59_fu_1113_p2" SOURCE="/home/ytq/codeField/Prediction_Model_Accelerator/CSIM/Sparse_HLS/Sparse_HLS/src/../include/helpers.hpp:59" VARIABLE="add_ln59" MODULE="mul_ap_uint_256_ap_int_8_ap_int_8_32u_s" LOOP="VITIS_LOOP_56_3" BUNDLEDNAME="" DSP="0" BRAM="0" URAM="0"/>
	<BindNode BINDTYPE="op" DISPLAY="bind_op add" ID="" IMPL="fabric" LATENCY="0" OPTYPE="add" PRAGMA="" RTLNAME="add_ln59_1_fu_1119_p2" SOURCE="/home/ytq/codeField/Prediction_Model_Accelerator/CSIM/Sparse_HLS/Sparse_HLS/src/../include/helpers.hpp:59" VARIABLE="add_ln59_1" MODULE="mul_ap_uint_256_ap_int_8_ap_int_8_32u_s" LOOP="VITIS_LOOP_56_3" BUNDLEDNAME="" DSP="0" BRAM="0" URAM="0"/>
	<BindNode BINDTYPE="op" DISPLAY="bind_op add" ID="" IMPL="fabric" LATENCY="0" OPTYPE="add" PRAGMA="" RTLNAME="add_ln59_2_fu_1145_p2" SOURCE="/home/ytq/codeField/Prediction_Model_Accelerator/CSIM/Sparse_HLS/Sparse_HLS/src/../include/helpers.hpp:59" VARIABLE="add_ln59_2" MODULE="mul_ap_uint_256_ap_int_8_ap_int_8_32u_s" LOOP="VITIS_LOOP_56_3" BUNDLEDNAME="" DSP="0" BRAM="0" URAM="0"/>
	<BindNode BINDTYPE="op" DISPLAY="bind_op add" ID="" IMPL="fabric" LATENCY="0" OPTYPE="add" PRAGMA="" RTLNAME="add_ln59_3_fu_1151_p2" SOURCE="/home/ytq/codeField/Prediction_Model_Accelerator/CSIM/Sparse_HLS/Sparse_HLS/src/../include/helpers.hpp:59" VARIABLE="add_ln59_3" MODULE="mul_ap_uint_256_ap_int_8_ap_int_8_32u_s" LOOP="VITIS_LOOP_56_3" BUNDLEDNAME="" DSP="0" BRAM="0" URAM="0"/>
	<BindNode BINDTYPE="op" DISPLAY="bind_op add" ID="" IMPL="fabric" LATENCY="0" OPTYPE="add" PRAGMA="" RTLNAME="add_ln59_4_fu_1177_p2" SOURCE="/home/ytq/codeField/Prediction_Model_Accelerator/CSIM/Sparse_HLS/Sparse_HLS/src/../include/helpers.hpp:59" VARIABLE="add_ln59_4" MODULE="mul_ap_uint_256_ap_int_8_ap_int_8_32u_s" LOOP="VITIS_LOOP_56_3" BUNDLEDNAME="" DSP="0" BRAM="0" URAM="0"/>
	<BindNode BINDTYPE="op" DISPLAY="bind_op add" ID="" IMPL="fabric" LATENCY="0" OPTYPE="add" PRAGMA="" RTLNAME="add_ln59_5_fu_1183_p2" SOURCE="/home/ytq/codeField/Prediction_Model_Accelerator/CSIM/Sparse_HLS/Sparse_HLS/src/../include/helpers.hpp:59" VARIABLE="add_ln59_5" MODULE="mul_ap_uint_256_ap_int_8_ap_int_8_32u_s" LOOP="VITIS_LOOP_56_3" BUNDLEDNAME="" DSP="0" BRAM="0" URAM="0"/>
	<BindNode BINDTYPE="op" DISPLAY="bind_op add" ID="" IMPL="fabric" LATENCY="0" OPTYPE="add" PRAGMA="" RTLNAME="add_ln59_6_fu_1209_p2" SOURCE="/home/ytq/codeField/Prediction_Model_Accelerator/CSIM/Sparse_HLS/Sparse_HLS/src/../include/helpers.hpp:59" VARIABLE="add_ln59_6" MODULE="mul_ap_uint_256_ap_int_8_ap_int_8_32u_s" LOOP="VITIS_LOOP_56_3" BUNDLEDNAME="" DSP="0" BRAM="0" URAM="0"/>
	<BindNode BINDTYPE="op" DISPLAY="bind_op add" ID="" IMPL="fabric" LATENCY="0" OPTYPE="add" PRAGMA="" RTLNAME="add_ln59_7_fu_1215_p2" SOURCE="/home/ytq/codeField/Prediction_Model_Accelerator/CSIM/Sparse_HLS/Sparse_HLS/src/../include/helpers.hpp:59" VARIABLE="add_ln59_7" MODULE="mul_ap_uint_256_ap_int_8_ap_int_8_32u_s" LOOP="VITIS_LOOP_56_3" BUNDLEDNAME="" DSP="0" BRAM="0" URAM="0"/>
	<BindNode BINDTYPE="op" DISPLAY="bind_op add" ID="" IMPL="fabric" LATENCY="0" OPTYPE="add" PRAGMA="" RTLNAME="add_ln59_8_fu_1241_p2" SOURCE="/home/ytq/codeField/Prediction_Model_Accelerator/CSIM/Sparse_HLS/Sparse_HLS/src/../include/helpers.hpp:59" VARIABLE="add_ln59_8" MODULE="mul_ap_uint_256_ap_int_8_ap_int_8_32u_s" LOOP="VITIS_LOOP_56_3" BUNDLEDNAME="" DSP="0" BRAM="0" URAM="0"/>
	<BindNode BINDTYPE="op" DISPLAY="bind_op add" ID="" IMPL="fabric" LATENCY="0" OPTYPE="add" PRAGMA="" RTLNAME="add_ln59_9_fu_1247_p2" SOURCE="/home/ytq/codeField/Prediction_Model_Accelerator/CSIM/Sparse_HLS/Sparse_HLS/src/../include/helpers.hpp:59" VARIABLE="add_ln59_9" MODULE="mul_ap_uint_256_ap_int_8_ap_int_8_32u_s" LOOP="VITIS_LOOP_56_3" BUNDLEDNAME="" DSP="0" BRAM="0" URAM="0"/>
	<BindNode BINDTYPE="op" DISPLAY="bind_op add" ID="" IMPL="fabric" LATENCY="0" OPTYPE="add" PRAGMA="" RTLNAME="add_ln59_10_fu_1273_p2" SOURCE="/home/ytq/codeField/Prediction_Model_Accelerator/CSIM/Sparse_HLS/Sparse_HLS/src/../include/helpers.hpp:59" VARIABLE="add_ln59_10" MODULE="mul_ap_uint_256_ap_int_8_ap_int_8_32u_s" LOOP="VITIS_LOOP_56_3" BUNDLEDNAME="" DSP="0" BRAM="0" URAM="0"/>
	<BindNode BINDTYPE="op" DISPLAY="bind_op add" ID="" IMPL="fabric" LATENCY="0" OPTYPE="add" PRAGMA="" RTLNAME="add_ln59_11_fu_1279_p2" SOURCE="/home/ytq/codeField/Prediction_Model_Accelerator/CSIM/Sparse_HLS/Sparse_HLS/src/../include/helpers.hpp:59" VARIABLE="add_ln59_11" MODULE="mul_ap_uint_256_ap_int_8_ap_int_8_32u_s" LOOP="VITIS_LOOP_56_3" BUNDLEDNAME="" DSP="0" BRAM="0" URAM="0"/>
	<BindNode BINDTYPE="op" DISPLAY="bind_op add" ID="" IMPL="fabric" LATENCY="0" OPTYPE="add" PRAGMA="" RTLNAME="add_ln59_12_fu_1305_p2" SOURCE="/home/ytq/codeField/Prediction_Model_Accelerator/CSIM/Sparse_HLS/Sparse_HLS/src/../include/helpers.hpp:59" VARIABLE="add_ln59_12" MODULE="mul_ap_uint_256_ap_int_8_ap_int_8_32u_s" LOOP="VITIS_LOOP_56_3" BUNDLEDNAME="" DSP="0" BRAM="0" URAM="0"/>
	<BindNode BINDTYPE="op" DISPLAY="bind_op add" ID="" IMPL="fabric" LATENCY="0" OPTYPE="add" PRAGMA="" RTLNAME="add_ln59_13_fu_1311_p2" SOURCE="/home/ytq/codeField/Prediction_Model_Accelerator/CSIM/Sparse_HLS/Sparse_HLS/src/../include/helpers.hpp:59" VARIABLE="add_ln59_13" MODULE="mul_ap_uint_256_ap_int_8_ap_int_8_32u_s" LOOP="VITIS_LOOP_56_3" BUNDLEDNAME="" DSP="0" BRAM="0" URAM="0"/>
	<BindNode BINDTYPE="op" DISPLAY="bind_op add" ID="" IMPL="fabric" LATENCY="0" OPTYPE="add" PRAGMA="" RTLNAME="add_ln59_14_fu_1337_p2" SOURCE="/home/ytq/codeField/Prediction_Model_Accelerator/CSIM/Sparse_HLS/Sparse_HLS/src/../include/helpers.hpp:59" VARIABLE="add_ln59_14" MODULE="mul_ap_uint_256_ap_int_8_ap_int_8_32u_s" LOOP="VITIS_LOOP_56_3" BUNDLEDNAME="" DSP="0" BRAM="0" URAM="0"/>
	<BindNode BINDTYPE="op" DISPLAY="bind_op add" ID="" IMPL="fabric" LATENCY="0" OPTYPE="add" PRAGMA="" RTLNAME="add_ln59_15_fu_1343_p2" SOURCE="/home/ytq/codeField/Prediction_Model_Accelerator/CSIM/Sparse_HLS/Sparse_HLS/src/../include/helpers.hpp:59" VARIABLE="add_ln59_15" MODULE="mul_ap_uint_256_ap_int_8_ap_int_8_32u_s" LOOP="VITIS_LOOP_56_3" BUNDLEDNAME="" DSP="0" BRAM="0" URAM="0"/>
	<BindNode BINDTYPE="op" DISPLAY="bind_op add" ID="" IMPL="fabric" LATENCY="0" OPTYPE="add" PRAGMA="" RTLNAME="add_ln59_16_fu_1369_p2" SOURCE="/home/ytq/codeField/Prediction_Model_Accelerator/CSIM/Sparse_HLS/Sparse_HLS/src/../include/helpers.hpp:59" VARIABLE="add_ln59_16" MODULE="mul_ap_uint_256_ap_int_8_ap_int_8_32u_s" LOOP="VITIS_LOOP_56_3" BUNDLEDNAME="" DSP="0" BRAM="0" URAM="0"/>
	<BindNode BINDTYPE="op" DISPLAY="bind_op add" ID="" IMPL="fabric" LATENCY="0" OPTYPE="add" PRAGMA="" RTLNAME="add_ln59_17_fu_1375_p2" SOURCE="/home/ytq/codeField/Prediction_Model_Accelerator/CSIM/Sparse_HLS/Sparse_HLS/src/../include/helpers.hpp:59" VARIABLE="add_ln59_17" MODULE="mul_ap_uint_256_ap_int_8_ap_int_8_32u_s" LOOP="VITIS_LOOP_56_3" BUNDLEDNAME="" DSP="0" BRAM="0" URAM="0"/>
	<BindNode BINDTYPE="op" DISPLAY="bind_op add" ID="" IMPL="fabric" LATENCY="0" OPTYPE="add" PRAGMA="" RTLNAME="add_ln59_18_fu_1401_p2" SOURCE="/home/ytq/codeField/Prediction_Model_Accelerator/CSIM/Sparse_HLS/Sparse_HLS/src/../include/helpers.hpp:59" VARIABLE="add_ln59_18" MODULE="mul_ap_uint_256_ap_int_8_ap_int_8_32u_s" LOOP="VITIS_LOOP_56_3" BUNDLEDNAME="" DSP="0" BRAM="0" URAM="0"/>
	<BindNode BINDTYPE="op" DISPLAY="bind_op add" ID="" IMPL="fabric" LATENCY="0" OPTYPE="add" PRAGMA="" RTLNAME="add_ln59_19_fu_1407_p2" SOURCE="/home/ytq/codeField/Prediction_Model_Accelerator/CSIM/Sparse_HLS/Sparse_HLS/src/../include/helpers.hpp:59" VARIABLE="add_ln59_19" MODULE="mul_ap_uint_256_ap_int_8_ap_int_8_32u_s" LOOP="VITIS_LOOP_56_3" BUNDLEDNAME="" DSP="0" BRAM="0" URAM="0"/>
	<BindNode BINDTYPE="op" DISPLAY="bind_op add" ID="" IMPL="fabric" LATENCY="0" OPTYPE="add" PRAGMA="" RTLNAME="add_ln59_20_fu_1433_p2" SOURCE="/home/ytq/codeField/Prediction_Model_Accelerator/CSIM/Sparse_HLS/Sparse_HLS/src/../include/helpers.hpp:59" VARIABLE="add_ln59_20" MODULE="mul_ap_uint_256_ap_int_8_ap_int_8_32u_s" LOOP="VITIS_LOOP_56_3" BUNDLEDNAME="" DSP="0" BRAM="0" URAM="0"/>
	<BindNode BINDTYPE="op" DISPLAY="bind_op add" ID="" IMPL="fabric" LATENCY="0" OPTYPE="add" PRAGMA="" RTLNAME="add_ln59_21_fu_1439_p2" SOURCE="/home/ytq/codeField/Prediction_Model_Accelerator/CSIM/Sparse_HLS/Sparse_HLS/src/../include/helpers.hpp:59" VARIABLE="add_ln59_21" MODULE="mul_ap_uint_256_ap_int_8_ap_int_8_32u_s" LOOP="VITIS_LOOP_56_3" BUNDLEDNAME="" DSP="0" BRAM="0" URAM="0"/>
	<BindNode BINDTYPE="op" DISPLAY="bind_op add" ID="" IMPL="fabric" LATENCY="0" OPTYPE="add" PRAGMA="" RTLNAME="add_ln59_22_fu_1465_p2" SOURCE="/home/ytq/codeField/Prediction_Model_Accelerator/CSIM/Sparse_HLS/Sparse_HLS/src/../include/helpers.hpp:59" VARIABLE="add_ln59_22" MODULE="mul_ap_uint_256_ap_int_8_ap_int_8_32u_s" LOOP="VITIS_LOOP_56_3" BUNDLEDNAME="" DSP="0" BRAM="0" URAM="0"/>
	<BindNode BINDTYPE="op" DISPLAY="bind_op add" ID="" IMPL="fabric" LATENCY="0" OPTYPE="add" PRAGMA="" RTLNAME="add_ln59_23_fu_1471_p2" SOURCE="/home/ytq/codeField/Prediction_Model_Accelerator/CSIM/Sparse_HLS/Sparse_HLS/src/../include/helpers.hpp:59" VARIABLE="add_ln59_23" MODULE="mul_ap_uint_256_ap_int_8_ap_int_8_32u_s" LOOP="VITIS_LOOP_56_3" BUNDLEDNAME="" DSP="0" BRAM="0" URAM="0"/>
	<BindNode BINDTYPE="op" DISPLAY="bind_op add" ID="" IMPL="fabric" LATENCY="0" OPTYPE="add" PRAGMA="" RTLNAME="add_ln59_24_fu_1497_p2" SOURCE="/home/ytq/codeField/Prediction_Model_Accelerator/CSIM/Sparse_HLS/Sparse_HLS/src/../include/helpers.hpp:59" VARIABLE="add_ln59_24" MODULE="mul_ap_uint_256_ap_int_8_ap_int_8_32u_s" LOOP="VITIS_LOOP_56_3" BUNDLEDNAME="" DSP="0" BRAM="0" URAM="0"/>
	<BindNode BINDTYPE="op" DISPLAY="bind_op add" ID="" IMPL="fabric" LATENCY="0" OPTYPE="add" PRAGMA="" RTLNAME="add_ln59_25_fu_1503_p2" SOURCE="/home/ytq/codeField/Prediction_Model_Accelerator/CSIM/Sparse_HLS/Sparse_HLS/src/../include/helpers.hpp:59" VARIABLE="add_ln59_25" MODULE="mul_ap_uint_256_ap_int_8_ap_int_8_32u_s" LOOP="VITIS_LOOP_56_3" BUNDLEDNAME="" DSP="0" BRAM="0" URAM="0"/>
	<BindNode BINDTYPE="op" DISPLAY="bind_op add" ID="" IMPL="fabric" LATENCY="0" OPTYPE="add" PRAGMA="" RTLNAME="add_ln59_26_fu_1529_p2" SOURCE="/home/ytq/codeField/Prediction_Model_Accelerator/CSIM/Sparse_HLS/Sparse_HLS/src/../include/helpers.hpp:59" VARIABLE="add_ln59_26" MODULE="mul_ap_uint_256_ap_int_8_ap_int_8_32u_s" LOOP="VITIS_LOOP_56_3" BUNDLEDNAME="" DSP="0" BRAM="0" URAM="0"/>
	<BindNode BINDTYPE="op" DISPLAY="bind_op add" ID="" IMPL="fabric" LATENCY="0" OPTYPE="add" PRAGMA="" RTLNAME="add_ln59_27_fu_1535_p2" SOURCE="/home/ytq/codeField/Prediction_Model_Accelerator/CSIM/Sparse_HLS/Sparse_HLS/src/../include/helpers.hpp:59" VARIABLE="add_ln59_27" MODULE="mul_ap_uint_256_ap_int_8_ap_int_8_32u_s" LOOP="VITIS_LOOP_56_3" BUNDLEDNAME="" DSP="0" BRAM="0" URAM="0"/>
	<BindNode BINDTYPE="op" DISPLAY="bind_op add" ID="" IMPL="fabric" LATENCY="0" OPTYPE="add" PRAGMA="" RTLNAME="add_ln59_28_fu_1561_p2" SOURCE="/home/ytq/codeField/Prediction_Model_Accelerator/CSIM/Sparse_HLS/Sparse_HLS/src/../include/helpers.hpp:59" VARIABLE="add_ln59_28" MODULE="mul_ap_uint_256_ap_int_8_ap_int_8_32u_s" LOOP="VITIS_LOOP_56_3" BUNDLEDNAME="" DSP="0" BRAM="0" URAM="0"/>
	<BindNode BINDTYPE="op" DISPLAY="bind_op add" ID="" IMPL="fabric" LATENCY="0" OPTYPE="add" PRAGMA="" RTLNAME="add_ln59_29_fu_1567_p2" SOURCE="/home/ytq/codeField/Prediction_Model_Accelerator/CSIM/Sparse_HLS/Sparse_HLS/src/../include/helpers.hpp:59" VARIABLE="add_ln59_29" MODULE="mul_ap_uint_256_ap_int_8_ap_int_8_32u_s" LOOP="VITIS_LOOP_56_3" BUNDLEDNAME="" DSP="0" BRAM="0" URAM="0"/>
	<BindNode BINDTYPE="op" DISPLAY="bind_op add" ID="" IMPL="fabric" LATENCY="0" OPTYPE="add" PRAGMA="" RTLNAME="add_ln59_30_fu_1573_p2" SOURCE="/home/ytq/codeField/Prediction_Model_Accelerator/CSIM/Sparse_HLS/Sparse_HLS/src/../include/helpers.hpp:59" VARIABLE="add_ln59_30" MODULE="mul_ap_uint_256_ap_int_8_ap_int_8_32u_s" LOOP="VITIS_LOOP_56_3" BUNDLEDNAME="" DSP="0" BRAM="0" URAM="0"/>
	<BindNode BINDTYPE="op" DISPLAY="bind_op add" ID="" IMPL="fabric" LATENCY="0" OPTYPE="add" PRAGMA="" RTLNAME="add_ln59_31_fu_1579_p2" SOURCE="/home/ytq/codeField/Prediction_Model_Accelerator/CSIM/Sparse_HLS/Sparse_HLS/src/../include/helpers.hpp:59" VARIABLE="add_ln59_31" MODULE="mul_ap_uint_256_ap_int_8_ap_int_8_32u_s" LOOP="VITIS_LOOP_56_3" BUNDLEDNAME="" DSP="0" BRAM="0" URAM="0"/>
	<BindNode BINDTYPE="op" DISPLAY="bind_op add" ID="" IMPL="fabric" LATENCY="0" OPTYPE="add" PRAGMA="" RTLNAME="idx_ram_base_1_fu_986_p2" SOURCE="/home/ytq/codeField/Prediction_Model_Accelerator/CSIM/Sparse_HLS/Sparse_HLS/src/../include/helpers.hpp:62" VARIABLE="idx_ram_base_1" MODULE="mul_ap_uint_256_ap_int_8_ap_int_8_32u_s" LOOP="VITIS_LOOP_51_2" BUNDLEDNAME="" DSP="0" BRAM="0" URAM="0"/>
	<BindNode BINDTYPE="op" DISPLAY="bind_op icmp" ID="" IMPL="auto" LATENCY="0" OPTYPE="icmp" PRAGMA="" RTLNAME="icmp_ln84_fu_98_p2" SOURCE="/home/ytq/codeField/Prediction_Model_Accelerator/CSIM/Sparse_HLS/Sparse_HLS/src/../include/helpers.hpp:84" VARIABLE="icmp_ln84" MODULE="store_ap_uint_256_ap_int_8_ap_int_8_32u_Pipeline_VITIS_LOOP_84_1" LOOP="VITIS_LOOP_84_1" BUNDLEDNAME="" DSP="0" BRAM="0" URAM="0"/>
	<BindNode BINDTYPE="op" DISPLAY="bind_op add" ID="" IMPL="fabric" LATENCY="0" OPTYPE="add" PRAGMA="" RTLNAME="add_ln84_fu_104_p2" SOURCE="/home/ytq/codeField/Prediction_Model_Accelerator/CSIM/Sparse_HLS/Sparse_HLS/src/../include/helpers.hpp:84" VARIABLE="add_ln84" MODULE="store_ap_uint_256_ap_int_8_ap_int_8_32u_Pipeline_VITIS_LOOP_84_1" LOOP="VITIS_LOOP_84_1" BUNDLEDNAME="" DSP="0" BRAM="0" URAM="0"/>
	<BindNode BINDTYPE="op" DISPLAY="bind_op mul" ID="" IMPL="auto" LATENCY="0" OPTYPE="mul" PRAGMA="" RTLNAME="mul_32s_32s_32_1_1_U31" SOURCE="/home/ytq/codeField/Prediction_Model_Accelerator/CSIM/Sparse_HLS/Sparse_HLS/src/../include/helpers.hpp:81" VARIABLE="mul_ln81" MODULE="store_ap_uint_256_ap_int_8_ap_int_8_32u_s" LOOP="" BUNDLEDNAME="" DSP="3" BRAM="0" URAM="0"/>
	<BindNode BINDTYPE="op" DISPLAY="bind_op icmp" ID="" IMPL="auto" LATENCY="0" OPTYPE="icmp" PRAGMA="" RTLNAME="icmp_ln84_fu_154_p2" SOURCE="/home/ytq/codeField/Prediction_Model_Accelerator/CSIM/Sparse_HLS/Sparse_HLS/src/../include/helpers.hpp:84" VARIABLE="icmp_ln84" MODULE="store_ap_uint_256_ap_int_8_ap_int_8_32u_s" LOOP="" BUNDLEDNAME="" DSP="0" BRAM="0" URAM="0"/>
	<BindNode BINDTYPE="op" DISPLAY="bind_op add" ID="" IMPL="fabric" LATENCY="0" OPTYPE="add" PRAGMA="" RTLNAME="add_ln84_fu_172_p2" SOURCE="/home/ytq/codeField/Prediction_Model_Accelerator/CSIM/Sparse_HLS/Sparse_HLS/src/../include/helpers.hpp:84" VARIABLE="add_ln84" MODULE="store_ap_uint_256_ap_int_8_ap_int_8_32u_s" LOOP="" BUNDLEDNAME="" DSP="0" BRAM="0" URAM="0"/>
	<BindNode BINDTYPE="op" DISPLAY="bind_op icmp" ID="" IMPL="auto" LATENCY="0" OPTYPE="icmp" PRAGMA="" RTLNAME="icmp_ln91_fu_198_p2" SOURCE="/home/ytq/codeField/Prediction_Model_Accelerator/CSIM/Sparse_HLS/Sparse_HLS/src/../include/helpers.hpp:91" VARIABLE="icmp_ln91" MODULE="store_ap_uint_256_ap_int_8_ap_int_8_32u_s" LOOP="" BUNDLEDNAME="" DSP="0" BRAM="0" URAM="0"/>
	<BindNode BINDTYPE="storage" DISPLAY="bind_storage fifo" ID="" IMPL="srl" LATENCY="0" OPTYPE="fifo" PRAGMA="" RTLNAME="outputs_c_U" SOURCE="/home/ytq/codeField/Prediction_Model_Accelerator/CSIM/Sparse_HLS/Sparse_HLS/src/sparse.cpp:36" VARIABLE="outputs_c" MODULE="sparse" LOOP="" BUNDLEDNAME="" DSP="0" BRAM="0" URAM="0"/>
	<BindNode BINDTYPE="storage" DISPLAY="bind_storage fifo" ID="" IMPL="srl" LATENCY="0" OPTYPE="fifo" PRAGMA="" RTLNAME="fm_COLS_c_U" SOURCE="/home/ytq/codeField/Prediction_Model_Accelerator/CSIM/Sparse_HLS/Sparse_HLS/src/sparse.cpp:36" VARIABLE="fm_COLS_c" MODULE="sparse" LOOP="" BUNDLEDNAME="" DSP="0" BRAM="0" URAM="0"/>
	<BindNode BINDTYPE="storage" DISPLAY="bind_storage fifo" ID="" IMPL="srl" LATENCY="0" OPTYPE="fifo" PRAGMA="" RTLNAME="am_ROWS_c_U" SOURCE="/home/ytq/codeField/Prediction_Model_Accelerator/CSIM/Sparse_HLS/Sparse_HLS/src/sparse.cpp:36" VARIABLE="am_ROWS_c" MODULE="sparse" LOOP="" BUNDLEDNAME="" DSP="0" BRAM="0" URAM="0"/>
	<BindNode BINDTYPE="storage" DISPLAY="bind_storage fifo" ID="" IMPL="srl" LATENCY="0" OPTYPE="fifo" PRAGMA="" RTLNAME="output_data_addr3_c_U" SOURCE="/home/ytq/codeField/Prediction_Model_Accelerator/CSIM/Sparse_HLS/Sparse_HLS/src/sparse.cpp:36" VARIABLE="output_data_addr3_c" MODULE="sparse" LOOP="" BUNDLEDNAME="" DSP="0" BRAM="0" URAM="0"/>
	<BindNode BINDTYPE="storage" DISPLAY="bind_storage fifo" ID="" IMPL="memory" LATENCY="0" OPTYPE="fifo" PRAGMA="" RTLNAME="data_out_U" SOURCE="/home/ytq/codeField/Prediction_Model_Accelerator/CSIM/Sparse_HLS/Sparse_HLS/src/sparse.cpp:29" VARIABLE="data_out" MODULE="sparse" LOOP="" BUNDLEDNAME="" DSP="0" BRAM="15" URAM="0"/>
	<BindNode BINDTYPE="storage" DISPLAY="bind_storage ram_s2p" ID="" IMPL="auto" LATENCY="1" OPTYPE="ram_s2p" PRAGMA="" RTLNAME="fm_ram_V_U" SOURCE="/home/ytq/codeField/Prediction_Model_Accelerator/CSIM/Sparse_HLS/Sparse_HLS/src/sparse.cpp:32" VARIABLE="fm_ram_V" MODULE="sparse" LOOP="" BUNDLEDNAME="" DSP="0" BRAM="16" URAM="0"/>
	<BindNode BINDTYPE="storage" DISPLAY="bind_storage ram_1p" ID="" IMPL="auto" LATENCY="1" OPTYPE="ram_1p" PRAGMA="" RTLNAME="idx_ram_U" SOURCE="/home/ytq/codeField/Prediction_Model_Accelerator/CSIM/Sparse_HLS/Sparse_HLS/src/sparse.cpp:33" VARIABLE="idx_ram" MODULE="sparse" LOOP="" BUNDLEDNAME="" DSP="0" BRAM="1" URAM="0"/>
	<BindNode BINDTYPE="storage" DISPLAY="bind_storage ram_1p" ID="" IMPL="auto" LATENCY="1" OPTYPE="ram_1p" PRAGMA="" RTLNAME="count_ram_U" SOURCE="/home/ytq/codeField/Prediction_Model_Accelerator/CSIM/Sparse_HLS/Sparse_HLS/src/sparse.cpp:34" VARIABLE="count_ram" MODULE="sparse" LOOP="" BUNDLEDNAME="" DSP="0" BRAM="0" URAM="0"/>
	<BindNode BINDTYPE="op" DISPLAY="bind_op fifo" ID="" IMPL="srl" LATENCY="0" OPTYPE="fifo" PRAGMA="" RTLNAME="am_ROWS_c9_channel_U" SOURCE="/home/ytq/codeField/Prediction_Model_Accelerator/CSIM/Sparse_HLS/Sparse_HLS/src/sparse.cpp:37" VARIABLE="am_ROWS_c9_channel" MODULE="sparse" LOOP="" BUNDLEDNAME="" DSP="0" BRAM="0" URAM="0"/>
	<BindNode BINDTYPE="op" DISPLAY="bind_op fifo" ID="" IMPL="srl" LATENCY="0" OPTYPE="fifo" PRAGMA="" RTLNAME="fm_COLS_c10_channel_U" SOURCE="/home/ytq/codeField/Prediction_Model_Accelerator/CSIM/Sparse_HLS/Sparse_HLS/src/sparse.cpp:37" VARIABLE="fm_COLS_c10_channel" MODULE="sparse" LOOP="" BUNDLEDNAME="" DSP="0" BRAM="0" URAM="0"/>
	<BindNode BINDTYPE="adapter" DISPLAY="bind_adapter axilite" ID="" IMPL="" LATENCY="" OPTYPE="" PRAGMA="yes" RTLNAME="sparse_addr_s_axi_U" SOURCE="" VARIABLE="" MODULE="sparse" LOOP="" BUNDLEDNAME="sparse_addr" DSP="0" BRAM="0" URAM="0"/>
	<BindNode BINDTYPE="adapter" DISPLAY="bind_adapter axi_master" ID="" IMPL="" LATENCY="" OPTYPE="" PRAGMA="yes" RTLNAME="sparse_data_m_axi_U" SOURCE="" VARIABLE="" MODULE="sparse" LOOP="" BUNDLEDNAME="sparse_data" DSP="0" BRAM="0" URAM="0"/>
</BindInfo>
